__init__.py
mathmatical_notation.py
ms_mathmaticalnotation-0.0.1.dist-info/licenses/LICENSE
ms_mathmaticalnotation-0.0.1.dist-info/METADATA
ms_mathmaticalnotation-0.0.1.dist-info/WHEEL
ms_mathmaticalnotation-0.0.1.dist-info/top_level.txt
ms_mathmaticalnotation-0.0.1.dist-info/RECORD
