Metadata-Version: 2.4
Name: ms_mathmaticalnotation
Version: 0.0.1
Summary: A packages for a mathmatical nations in a data-structure
Author-email: Mohammad Sadeghi <mohammadsadeghi1082@gmail.com>
License-Expression: MIT
Project-URL: Homepage, https://github.com/mohammadaitech
Project-URL: Issues, https://github.com/pypa/sampleproject/issues
Classifier: Programming Language :: Python :: 3
Classifier: Operating System :: OS Independent
Requires-Python: >=3.8
License-File: LICENSE
Dynamic: license-file
